{
  "-KI7VQ6ZoUc6xx6R48w8": {
    "-K-sgXF7SQ_R5n1_F-Lv": {
      "author": {
        "key": "-K-sgXF6kcVNbkMTnm8g",
        "name": "C-3PO"
      },
      "created": "1970-01-08T20:02:00-07:00",
      "text": "This asteroid may not be entirely stable."
    },
    "-K-sgXFJdks9Gomydal0": {
      "author": {
        "key": "-K-sgXF6kcVNbkMTnm8g",
        "name": "C-3PO"
      },
      "created": "1970-01-08T15:46:23-07:00",
      "text": "R2 is a rusty bucket of bolts! j/k"
    },
    "-K-sgXFMwFyoV1vfxawd": {
      "author": {
        "key": "-K-sgXF6kcVNbkMTnm8g",
        "name": "C-3PO"
      },
      "created": "1970-01-07T02:43:46-07:00",
      "text": "Just call me Golden Rod"
    }
  },
  "-KI7VQ6_Iu6mHdO-LKbq": {
    "-K-sgXFXG3eDCfTdPJNF": {
      "author": {
        "key": "-K-sgXFWAuXU4iN4Uwv-",
        "name": "Luke Skywalker"
    },
      "created": "1970-01-10T22:16:21-07:00",
      "text": "Ugh! My life is going nowhere!"
    },
    "-K-sgXF_vVrhh4_Rqy62": {
      "author": {
        "key": "-K-sgXFWAuXU4iN4Uwv-",
        "name": "Luke Skywalker"
      },
      "created": "1970-01-13T15:16:09-07:00",
      "text": "Hey @Biggs, let's go shoot womp rats. I'll tell my uncle that we're picking up power converters, hehe."
    },
    "-K-sgXFcn1EJSpbZs0Rs": {
      "author": {
        "key": "-K-sgXFWAuXU4iN4Uwv-",
        "name": "Luke Skywalker"
      },
      "created": "1970-01-03T02:55:53-07:00",
      "text": "Best thing about two suns? Nothing."
    }
  },
  "-KI7VQ6asReZ0cGgzM_y": {
    "-K-sgXFhA6ngWY_NUSBq": {
      "author": {
        "key": "-K-sgXFe_iwLRDLrMVf2",
        "name": "R2-D2"
      },
      "created": "1970-01-03T16:19:43-07:00",
      "text": "Beep Beep Boop!"
    },
    "-K-sgXFkvlDwnd0cdFQT": {
      "author": {
        "key": "-K-sgXFe_iwLRDLrMVf2",
        "name": "R2-D2"
      },
      "created": "1970-01-05T11:36:27-07:00",
      "text": "Click Whir Beep!"
    },
    "-K-sgXFpCeDcc37btCc0": {
      "author": {
        "key": "-K-sgXFe_iwLRDLrMVf2",
        "name": "R2-D2"
      },
      "created": "1970-01-07T02:13:35-07:00",
      "text": "Beep Click Beep!"
    }
  },
  "-KISHXHxsvh3Wmq4LkoC": {
    "-K-sgXFwMdj_CPmLWKpr": {
      "author": {
        "key": "-K-sgXFwMdj_CPmLWKpq",
        "name": "Darth Vader"
      },
      "created": "1970-01-05T03:20:02-07:00",
      "text": "Are you choking on something?"
    },
    "-K-sgXFyn3KRlE6pXxdG": {
      "author": {
        "key": "-K-sgXFwMdj_CPmLWKpq",
        "name": "Darth Vader"
      },
      "created": "1970-01-14T15:14:25-07:00",
      "text": "I find your lack of faith disturbing"
    },
    "-K-sgXG-uXrEifYx1Q1O": {
      "author": {
        "key": "-K-sgXFwMdj_CPmLWKpq",
        "name": "Darth Vader"
      },
      "created": "1970-01-02T18:07:31-07:00",
      "text": "Found a lost puppy. Home is the hidden rebel base. Anyone know where that is?"
    }
  }
}




